blob_pandas/__init__.py
blob_pandas/__version__.py
blob_pandas/blob_io.py
blob_pandas-0.1.4.dist-info/LICENSE
blob_pandas-0.1.4.dist-info/METADATA
blob_pandas-0.1.4.dist-info/WHEEL
blob_pandas-0.1.4.dist-info/RECORD
